cron_command/__init__.py
cron_command/apps.py
cron_command/management/__init__.py
cron_command/management/commands/__init__.py
cron_command/management/commands/cron_add.py
cron_command/management/commands/cron_list.py
cron_command/management/commands/cron_remove.py
django_cron_command-0.1.0.dist-info/LICENSE
django_cron_command-0.1.0.dist-info/METADATA
django_cron_command-0.1.0.dist-info/WHEEL
django_cron_command-0.1.0.dist-info/top_level.txt
django_cron_command-0.1.0.dist-info/RECORD
