Metadata-Version: 2.1
Name: django-cron-command
Version: 0.1.0
Summary: A Django app to manage cron jobs.
Home-page: https://github.com/Faruk-Hossain-1101/django-cron-command
Author: Faruk Hossain
Author-email: hossainf114@gmail.com
License: MIT
Classifier: Development Status :: 4 - Beta
Classifier: Intended Audience :: Developers
Classifier: License :: OSI Approved :: MIT License
Classifier: Programming Language :: Python :: 3
Classifier: Framework :: Django
Requires-Python: >=3.6
License-File: LICENSE
Requires-Dist: Django >=3.0
